{"cameraMode":{"drawMode":0,"name":"Shaded","section":"Shading Mode"},"sceneLighting":true,"audioPlay":false,"sceneViewState":{"m_AlwaysRefresh":false,"showFog":true,"showSkybox":true,"showFlares":true,"showImageEffects":true,"showParticleSystems":true,"showVisualEffectGraphs":true,"m_FxEnabled":true},"in2DMode":false,"pivot":{"x":-1.6625803709030152,"y":0.8437028527259827,"z":-2.0760040283203127},"rotation":{"x":-0.1219153180718422,"y":0.8370384573936462,"z":-0.49134302139282229,"w":-0.20767110586166383},"size":1.1517969369888306,"orthographic":false}